auto_pytester/__init__.py
auto_pytester/cli.py
auto_pytester/src/generator.py
auto_pytester/src/scanner.py
auto_pytester/templates/class_test_template.j2
auto_pytester/templates/conftest_template.j2
auto_pytester/templates/func_test_template.j2
auto_pytester/utils/decorator.py
src_demo/calc.py
src_demo/extension/apoc.py
tests-auto/conftest.py
tests-auto/test_Calc.py
tests-auto/test_cx.py
tests-auto/test_extract_examples.py
auto_pytester-0.1.4.dist-info/METADATA
auto_pytester-0.1.4.dist-info/WHEEL
auto_pytester-0.1.4.dist-info/entry_points.txt
auto_pytester-0.1.4.dist-info/top_level.txt
auto_pytester-0.1.4.dist-info/RECORD
